MANIFEST.in
README.txt
setup.py
docs/HISTORY.txt
docs/LICENSE.txt
src/silva/__init__.py
src/silva.translations.egg-info/PKG-INFO
src/silva.translations.egg-info/SOURCES.txt
src/silva.translations.egg-info/dependency_links.txt
src/silva.translations.egg-info/namespace_packages.txt
src/silva.translations.egg-info/not-zip-safe
src/silva.translations.egg-info/requires.txt
src/silva.translations.egg-info/top_level.txt
src/silva/translations/__init__.py
src/silva/translations/configure.zcml
src/silva/translations/languages.py
src/silva/translations/negotiate.py
src/silva/translations/i18n/README.txt
src/silva/translations/i18n/silva.pot
src/silva/translations/i18n/ar/LC_MESSAGES/silva.mo
src/silva/translations/i18n/ar/LC_MESSAGES/silva.po
src/silva/translations/i18n/bn/LC_MESSAGES/silva.mo
src/silva/translations/i18n/bn/LC_MESSAGES/silva.po
src/silva/translations/i18n/bs/LC_MESSAGES/silva.mo
src/silva/translations/i18n/bs/LC_MESSAGES/silva.po
src/silva/translations/i18n/ca/LC_MESSAGES/silva.mo
src/silva/translations/i18n/ca/LC_MESSAGES/silva.po
src/silva/translations/i18n/cs/LC_MESSAGES/silva.mo
src/silva/translations/i18n/cs/LC_MESSAGES/silva.po
src/silva/translations/i18n/da/LC_MESSAGES/silva.mo
src/silva/translations/i18n/da/LC_MESSAGES/silva.po
src/silva/translations/i18n/de/LC_MESSAGES/silva.mo
src/silva/translations/i18n/de/LC_MESSAGES/silva.po
src/silva/translations/i18n/dv/LC_MESSAGES/silva.mo
src/silva/translations/i18n/dv/LC_MESSAGES/silva.po
src/silva/translations/i18n/el/LC_MESSAGES/silva.mo
src/silva/translations/i18n/el/LC_MESSAGES/silva.po
src/silva/translations/i18n/en/LC_MESSAGES/silva.mo
src/silva/translations/i18n/en/LC_MESSAGES/silva.po
src/silva/translations/i18n/en_GB/LC_MESSAGES/silva.mo
src/silva/translations/i18n/en_GB/LC_MESSAGES/silva.po
src/silva/translations/i18n/es/LC_MESSAGES/silva.mo
src/silva/translations/i18n/es/LC_MESSAGES/silva.po
src/silva/translations/i18n/et/LC_MESSAGES/silva.mo
src/silva/translations/i18n/et/LC_MESSAGES/silva.po
src/silva/translations/i18n/fa/LC_MESSAGES/silva.mo
src/silva/translations/i18n/fa/LC_MESSAGES/silva.po
src/silva/translations/i18n/fa_AF/LC_MESSAGES/silva.mo
src/silva/translations/i18n/fa_AF/LC_MESSAGES/silva.po
src/silva/translations/i18n/fi/LC_MESSAGES/silva.mo
src/silva/translations/i18n/fi/LC_MESSAGES/silva.po
