Metadata-Version: 1.1
Name: silva.translations
Version: 3.0.2
Summary: Translations files in many languages for the Silva CMS
Home-page: https://github.com/silvacms/silva.translations
Author: Infrae
Author-email: info@infrae.com
License: BSD
Keywords: silva translations
Platform: UNKNOWN
Classifier: Framework :: Zope2
Classifier: License :: OSI Approved :: BSD License
Classifier: Programming Language :: Python
Classifier: Topic :: Software Development :: Libraries :: Python Modules
